TA7291P_driver/TA7291P_driver.py
TA7291P_driver/__init__.py
TA7291P_driver-0.0.3.dist-info/LICENSE
TA7291P_driver-0.0.3.dist-info/METADATA
TA7291P_driver-0.0.3.dist-info/WHEEL
TA7291P_driver-0.0.3.dist-info/top_level.txt
TA7291P_driver-0.0.3.dist-info/RECORD
